commitcli/__init__.py
commitcli/__main__.py
commitcli/commit_message.py
commitcli/commitcli.py
commitcli/common.py
common/__init__.py
common/constants.py
common/environment.py
common/functions.py
common/logger.py
common/versions.py
configmanager/__init__.py
configmanager/config.py
configmanager/config_manager.py
configmanager/format_module_manager.py
configmanager/test_configmanager.py
configmanager/test_format_module_manager.py
data/__init__.py
data/db.py
data/modules_repository.py
tests/__init__.py
commitcli-1.5.5.dist-info/METADATA
commitcli-1.5.5.dist-info/WHEEL
commitcli-1.5.5.dist-info/entry_points.txt
commitcli-1.5.5.dist-info/top_level.txt
commitcli-1.5.5.dist-info/RECORD
