Metadata-Version: 2.4
Name: commitcli
Version: 1.5.5
Summary: commitcli is a cli to quick format your commits using conventional commits, odoo format or semantic git commits
Home-page: https://github.com/marco-gallegos/commit-cli
Author: Marco A. Gallegos
Author-email: ma_galeza@hotmail.com
License: MIT
Requires-Python: >=3.12
Requires-Dist: inquirer
Requires-Dist: click
Requires-Dist: loguru
Requires-Dist: pendulum
Requires-Dist: pygit2==1.13.0
Requires-Dist: pymongo
Requires-Dist: python-dotenv
Dynamic: author
Dynamic: author-email
Dynamic: home-page
Dynamic: requires-python
